[
    {
        "blood": "B-",
        "contact": "01621961907",
        "donation_date": "2023-06-24",
        "loaction": "pabna",
        "previous_date": "2023-06-02"
    },
    {
        "blood": "B+",
        "contact": "01621961907",
        "donation_date": "2023-06-24",
        "loaction": "pabna",
        "previous_date": "2023-06-02"
    },
    {
        "blood": "A-",
        "contact": "01621961907",
        "donation_date": "2023-06-24",
        "loaction": "pabna",
        "previous_date": "2023-06-02"
    },
    {
        "blood": "A+",
        "contact": "01621961907",
        "donation_date": "2023-06-24",
        "loaction": "pabna",
        "previous_date": "2023-06-02"
    },
    {
        "blood": "O-",
        "contact": "01621961907",
        "donation_date": "2023-06-24",
        "loaction": "pabna",
        "previous_date": "2023-06-02"
    },
    {
        "blood": "O+",
        "contact": "01621961907",
        "donation_date": "2023-06-24",
        "loaction": "pabna",
        "previous_date": "2023-06-02"
    },
    {
        "blood": "AB-",
        "contact": "01621961907",
        "donation_date": "2023-06-24",
        "loaction": "pabna",
        "previous_date": "2023-06-02"
    },
    {
        "blood": "AB+",
        "contact": "01621961907",
        "donation_date": "2023-06-24",
        "loaction": "pabna",
        "previous_date": "2023-06-02"
    }
]